dvc_utils/__init__.py
dvc_utils/cli.py
dvc_utils/diff.py
dvc_utils/main.py
dvc_utils/path.py
dvc_utils/sync.py
dvc_utils-0.3.2.dist-info/METADATA
dvc_utils-0.3.2.dist-info/WHEEL
dvc_utils-0.3.2.dist-info/entry_points.txt
dvc_utils-0.3.2.dist-info/licenses/LICENSE
dvc_utils-0.3.2.dist-info/RECORD
