Metadata-Version: 2.4
Name: dvc-utils
Version: 0.3.2
Summary: CLI for diffing DVC-tracked files at two commits (or one commit vs. current worktree), optionally passing both through another command first
Project-URL: Homepage, https://github.com/runsascoded/dvc-utils
Project-URL: Author URL, https://github.com/ryan-williams
Author-email: Ryan Williams <ryan@runsascoded.com>
License: MIT
License-File: LICENSE
Requires-Python: >=3.10
Requires-Dist: click
Requires-Dist: dffs>=0.0.7
Requires-Dist: pyyaml
Requires-Dist: utz>=0.20.0
Provides-Extra: ci
Requires-Dist: bmdf==0.5.2; extra == 'ci'
Requires-Dist: dvc-s3; extra == 'ci'
Provides-Extra: test
Requires-Dist: pytest>=7.0.0; extra == 'test'
